fdspy/__init__.py
fdspy/cli.py
fdspy/fds_cls.py
fdspy/calc_mtr/__init__.py
fdspy/calc_mtr/__main__.py
fdspy/calc_sprinkler/__init__.py
fdspy/calc_sprinkler/__main__.py
fdspy/fdsback/__init__.py
fdspy/fdsback/__main__.py
fdspy/fdsbginfo/__init__.py
fdspy/fdsbginfo/__main__.py
fdspy/fdsfront/__init__.py
fdspy/fdsfront/__main__.py
fdspy/gen_devc/__init__.py
fdspy/gen_devc/__main__.py
fdspy/lib/__init__.py
fdspy/lib/cibse_guide_e.py
fdspy/lib/fds_script_proc_analyser.py
fdspy/lib/fds_script_proc_data.py
fdspy/lib/fds_script_proc_decoder.py
fdspy/lib/func.py
fdspy/lib/func_.py
fdspy/lib/gui.py
fdspy-0.0.20.dist-info/LICENSE
fdspy-0.0.20.dist-info/METADATA
fdspy-0.0.20.dist-info/WHEEL
fdspy-0.0.20.dist-info/entry_points.txt
fdspy-0.0.20.dist-info/top_level.txt
fdspy-0.0.20.dist-info/RECORD
